controller/__init__.py
controller/main.py
controller_reader-0.1.4.dist-info/METADATA
controller_reader-0.1.4.dist-info/WHEEL
controller_reader-0.1.4.dist-info/top_level.txt
controller_reader-0.1.4.dist-info/RECORD
