Metadata-Version: 2.4
Name: controller-reader
Version: 0.1.4
Summary: Add your description here
Requires-Python: >=3.12
Requires-Dist: pygame>=2.6.1
